text2text/__init__.py
text2text/assistant.py
text2text/bm25er.py
text2text/composite_indexer.py
text2text/counter.py
text2text/handler.py
text2text/identifier.py
text2text/indexer.py
text2text/measurer.py
text2text/rag_assistant.py
text2text/sft.py
text2text/tfidfer.py
text2text/tokenizer.py
text2text/transformer.py
text2text/translator.py
text2text/variator.py
text2text/vectorizer.py
text2text-1.9.5.dist-info/LICENSE.txt
text2text-1.9.5.dist-info/METADATA
text2text-1.9.5.dist-info/WHEEL
text2text-1.9.5.dist-info/top_level.txt
text2text-1.9.5.dist-info/RECORD
