Metadata-Version: 2.2
Name: text2text
Version: 1.9.5
Summary: Text2Text Language Modeling Toolkit
Home-page: https://github.com/artitw/text2text
Author: artitw
Author-email: artitw@gmail.com
Keywords: multilingual gpt chatgpt bert natural language processing nlp nlg text generation gpt question answer answering information retrieval tfidf tf-idf bm25 search index summary summarizer summarization tokenizer tokenization translation backtranslation data augmentation science machine learning colab embedding levenshtein sub-word edit distance conversational dialog chatbot llama rag
Classifier: Programming Language :: Python :: 3
Classifier: License :: OSI Approved :: MIT License
Classifier: Operating System :: OS Independent
License-File: LICENSE.txt
Requires-Dist: faiss-cpu
Requires-Dist: beautifulsoup4
Requires-Dist: psutil
Requires-Dist: vllm
Requires-Dist: openai
Requires-Dist: numpy
Requires-Dist: pandas
Requires-Dist: pydantic
Requires-Dist: scikit-learn
Requires-Dist: scipy
Requires-Dist: sentencepiece
Requires-Dist: torch
Requires-Dist: triton
Requires-Dist: tqdm
Requires-Dist: transformers
Requires-Dist: peft
Requires-Dist: bitsandbytes
Requires-Dist: trl
Dynamic: author
Dynamic: author-email
Dynamic: classifier
Dynamic: description
Dynamic: description-content-type
Dynamic: home-page
Dynamic: keywords
Dynamic: requires-dist
Dynamic: summary
